head_require/__init__.py
head_require/core.py
head_require-2.2.24.dist-info/LICENSE
head_require-2.2.24.dist-info/METADATA
head_require-2.2.24.dist-info/WHEEL
head_require-2.2.24.dist-info/entry_points.txt
head_require-2.2.24.dist-info/top_level.txt
head_require-2.2.24.dist-info/RECORD
