Metadata-Version: 2.1
Name: head_require
Version: 2.2.24
Summary: head-require is a library that aims to simplify the creation of requirements.txt files. head-require generates requirements.txt based on the packages actually used in your project.
Home-page: https://github.com/Thanaraklee/Head-Require
Author: Thanarak Leenanon
Author-email: bzank.lee@hotmail.com
License: MIT
Classifier: Programming Language :: Python :: 3
Classifier: Development Status :: 4 - Beta
Classifier: License :: OSI Approved :: MIT License
Classifier: Operating System :: OS Independent
License-File: LICENSE
